EulerPy/__init__.py
EulerPy/__main__.py
EulerPy/euler.py
EulerPy/problem.py
EulerPy/utils.py
EulerPy/data/problems.txt
EulerPy/data/resources.json
EulerPy/data/solutions.txt
EulerPy/data/resources/202_laserbeam.gif
EulerPy/data/resources/208_robotwalk.gif
EulerPy/data/resources/215_crackfree.gif
EulerPy/data/resources/220.gif
EulerPy/data/resources/226_formula.gif
EulerPy/data/resources/226_scoop2.gif
EulerPy/data/resources/228.png
EulerPy/data/resources/237.gif
EulerPy/data/resources/244_example.gif
EulerPy/data/resources/244_start.gif
EulerPy/data/resources/244_target.gif
EulerPy/data/resources/246_anim.gif
EulerPy/data/resources/246_ellipse.gif
EulerPy/data/resources/247_hypersquares.gif
EulerPy/data/resources/251_cardano.gif
EulerPy/data/resources/252_convexhole.gif
EulerPy/data/resources/255_Example.gif
EulerPy/data/resources/255_Heron.gif
EulerPy/data/resources/256_tatami3.gif
EulerPy/data/resources/257_bisector.gif
EulerPy/data/resources/262_formula1.gif
EulerPy/data/resources/264_TriangleCentres.gif
EulerPy/data/resources/265_BinaryCircles.gif
EulerPy/data/resources/270_CutSquare.gif
EulerPy/data/resources/275_sculptures2.gif
EulerPy/data/resources/281_pizza.gif
EulerPy/data/resources/282_formula.gif
EulerPy/data/resources/287_quadtree.gif
EulerPy/data/resources/289_euler.gif
EulerPy/data/resources/291_formula.gif
EulerPy/data/resources/295_lenticular.gif
EulerPy/data/resources/299_ThreeSimTri.gif
EulerPy/data/resources/300_protein.gif
EulerPy/data/resources/306_pstrip.gif
EulerPy/data/resources/309_ladders.gif
EulerPy/data/resources/311_biclinic.gif
EulerPy/data/resources/312_sierpinsky8t.gif
EulerPy/data/resources/312_sierpinskyAt.gif
EulerPy/data/resources/313_sliding_game_1.gif
EulerPy/data/resources/313_sliding_game_2.gif
EulerPy/data/resources/314_landgrab.gif
EulerPy/data/resources/315_clocks.gif
EulerPy/data/resources/321_swapping_counters_1.gif
EulerPy/data/resources/321_swapping_counters_2.gif
EulerPy/data/resources/326_formula1.gif
EulerPy-1.4.0.dist-info/LICENSE
EulerPy-1.4.0.dist-info/METADATA
EulerPy-1.4.0.dist-info/WHEEL
EulerPy-1.4.0.dist-info/entry_points.txt
EulerPy-1.4.0.dist-info/top_level.txt
EulerPy-1.4.0.dist-info/RECORD
