Metadata-Version: 2.1
Name: EulerPy
Version: 1.4.0
Summary: Python-based Project Euler command line tool.
Home-page: https://github.com/iKevinY/EulerPy
Author: Kevin Yap
Author-email: me@kevinyap.ca
License: MIT
Keywords: EulerPy,euler,project-euler,projecteuler
Platform: UNKNOWN
Classifier: License :: OSI Approved :: MIT License
Classifier: Topic :: Utilities
Classifier: Programming Language :: Python
Classifier: Programming Language :: Python :: 2
Classifier: Programming Language :: Python :: 2.7
Classifier: Programming Language :: Python :: 3
Classifier: Programming Language :: Python :: 3.5
Classifier: Programming Language :: Python :: 3.6
Classifier: Programming Language :: Python :: 3.7
Classifier: Programming Language :: Python :: 3.8
Requires-Dist: click (==4.0)
